cisc_sections/__init__.py
cisc_sections/default_section_class.py
cisc_sections/sections.py
cisc_sections/steel_sections.py
cisc_sections/sections/2L-EL.pkl
cisc_sections/sections/2L-LL.pkl
cisc_sections/sections/2L-SL.pkl
cisc_sections/sections/C.pkl
cisc_sections/sections/HP.pkl
cisc_sections/sections/HSS(A500)-REC.pkl
cisc_sections/sections/HSS(A500)-ROUND.pkl
cisc_sections/sections/HSS(A500)-SQ.pkl
cisc_sections/sections/HSS(G40)-REC.pkl
cisc_sections/sections/HSS(G40)-ROUND.pkl
cisc_sections/sections/HSS(G40)-SQ.pkl
cisc_sections/sections/L.pkl
cisc_sections/sections/M.pkl
cisc_sections/sections/MC.pkl
cisc_sections/sections/S.pkl
cisc_sections/sections/SLB.pkl
cisc_sections/sections/W.pkl
cisc_sections/sections/WRF.pkl
cisc_sections/sections/WT.pkl
cisc_sections/sections/WWF.pkl
cisc_sections/sections/WWT.pkl
cisc_sections/sections/title.json
cisc_sections-0.0.4.dist-info/LICENSE
cisc_sections-0.0.4.dist-info/WHEEL
cisc_sections-0.0.4.dist-info/METADATA
cisc_sections-0.0.4.dist-info/RECORD
